delenie/__init__.py
delenie/main.py
delenie-0.1.dist-info/licenses/LICENSE
delenie-0.1.dist-info/METADATA
delenie-0.1.dist-info/WHEEL
delenie-0.1.dist-info/top_level.txt
delenie-0.1.dist-info/RECORD
